geomie3d/__init__.py
geomie3d/calculate.py
geomie3d/conftest.py
geomie3d/create.py
geomie3d/d4pispace.py
geomie3d/earcut.py
geomie3d/geom.py
geomie3d/get.py
geomie3d/modify.py
geomie3d/settings.py
geomie3d/topobj.py
geomie3d/utility.py
geomie3d/viz.py
geomie3d/geomdl/BSpline.py
geomie3d/geomdl/CPGen.py
geomie3d/geomdl/NURBS.py
geomie3d/geomdl/__init__.py
geomie3d/geomdl/_convert.py
geomie3d/geomdl/_exchange.py
geomie3d/geomdl/_linalg.py
geomie3d/geomdl/_operations.py
geomie3d/geomdl/_tessellate.py
geomie3d/geomdl/_utilities.py
geomie3d/geomdl/_voxelize.py
geomie3d/geomdl/abstract.py
geomie3d/geomdl/compatibility.py
geomie3d/geomdl/construct.py
geomie3d/geomdl/control_points.py
geomie3d/geomdl/convert.py
geomie3d/geomdl/elements.py
geomie3d/geomdl/evaluators.py
geomie3d/geomdl/exceptions.py
geomie3d/geomdl/exchange.py
geomie3d/geomdl/exchange_vtk.py
geomie3d/geomdl/fitting.py
geomie3d/geomdl/freeform.py
geomie3d/geomdl/functools_lru_cache.py
geomie3d/geomdl/helpers.py
geomie3d/geomdl/knotvector.py
geomie3d/geomdl/linalg.py
geomie3d/geomdl/multi.py
geomie3d/geomdl/operations.py
geomie3d/geomdl/ray.py
geomie3d/geomdl/shortcuts.py
geomie3d/geomdl/sweeping.py
geomie3d/geomdl/tessellate.py
geomie3d/geomdl/trimming.py
geomie3d/geomdl/utilities.py
geomie3d/geomdl/vis.py
geomie3d/geomdl/voxelize.py
geomie3d/geomdl/visualization/VisMPL.py
geomie3d/geomdl/visualization/VisPlotly.py
geomie3d/geomdl/visualization/VisVTK.py
geomie3d/geomdl/visualization/__init__.py
geomie3d/geomdl/visualization/vtk_helpers.py
geomie3d-0.0.11.dist-info/licenses/LICENSE
geomie3d-0.0.11.dist-info/METADATA
geomie3d-0.0.11.dist-info/WHEEL
geomie3d-0.0.11.dist-info/top_level.txt
geomie3d-0.0.11.dist-info/RECORD
