Metadata-Version: 2.4
Name: geomie3d
Version: 0.0.11
Summary: Python library for processing 3d geometry
Author-email: Kian Wee CHEN <chenkianwee@gmail.com>
Project-URL: Homepage, https://github.com/chenkianwee/geomie3d
Project-URL: Bug Tracker, https://github.com/chenkianwee/geomie3d/issues
Classifier: License :: OSI Approved :: GNU General Public License v3 (GPLv3)
Classifier: Programming Language :: Python :: 3.10
Classifier: Operating System :: OS Independent
Requires-Python: >=3.10
License-File: LICENSE
Requires-Dist: numpy>=1.26.4
Provides-Extra: viewer3d
Requires-Dist: pyqtgraph==0.13.7; extra == "viewer3d"
Requires-Dist: PyOpenGL==3.1.10; extra == "viewer3d"
Requires-Dist: PySide6==6.9.2; extra == "viewer3d"
Requires-Dist: python-dateutil==2.9.0; extra == "viewer3d"
Dynamic: license-file
